PytorchZiranyuyanChuliFix1Fix1/README.md
PytorchZiranyuyanChuliFix1Fix1/__init__.py
PytorchZiranyuyanChuliFix1Fix1/__main__.py
PytorchZiranyuyanChuliFix1Fix1/file.epub
PytorchZiranyuyanChuliFix1Fix1/index.html
PytorchZiranyuyanChuliFix1Fix1/css/__init__.py
PytorchZiranyuyanChuliFix1Fix1/css/annotations.css
PytorchZiranyuyanChuliFix1Fix1/css/main.css
PytorchZiranyuyanChuliFix1Fix1/css/normalize.css
PytorchZiranyuyanChuliFix1Fix1/css/popup.css
PytorchZiranyuyanChuliFix1Fix1/font/__init__.py
PytorchZiranyuyanChuliFix1Fix1/font/fontello.eot
PytorchZiranyuyanChuliFix1Fix1/font/fontello.svg
PytorchZiranyuyanChuliFix1Fix1/font/fontello.ttf
PytorchZiranyuyanChuliFix1Fix1/font/fontello.woff
PytorchZiranyuyanChuliFix1Fix1/img/__init__.py
PytorchZiranyuyanChuliFix1Fix1/img/annotator-glyph-sprite.png
PytorchZiranyuyanChuliFix1Fix1/img/annotator-icon-sprite.png
PytorchZiranyuyanChuliFix1Fix1/img/apple-touch-icon.png
PytorchZiranyuyanChuliFix1Fix1/img/cancelfullscreen.png
PytorchZiranyuyanChuliFix1Fix1/img/close.png
PytorchZiranyuyanChuliFix1Fix1/img/fullscreen.png
PytorchZiranyuyanChuliFix1Fix1/img/loader.gif
PytorchZiranyuyanChuliFix1Fix1/img/menu-icon.png
PytorchZiranyuyanChuliFix1Fix1/img/save.png
PytorchZiranyuyanChuliFix1Fix1/img/saved.png
PytorchZiranyuyanChuliFix1Fix1/img/settings-s.png
PytorchZiranyuyanChuliFix1Fix1/img/settings.png
PytorchZiranyuyanChuliFix1Fix1/img/star.png
PytorchZiranyuyanChuliFix1Fix1/js/__init__.py
PytorchZiranyuyanChuliFix1Fix1/js/epub.js
PytorchZiranyuyanChuliFix1Fix1/js/epub.min.js
PytorchZiranyuyanChuliFix1Fix1/js/epub.min.map
PytorchZiranyuyanChuliFix1Fix1/js/hooks.min.js
PytorchZiranyuyanChuliFix1Fix1/js/hooks.min.map
PytorchZiranyuyanChuliFix1Fix1/js/reader.js
PytorchZiranyuyanChuliFix1Fix1/js/reader.js.map
PytorchZiranyuyanChuliFix1Fix1/js/reader.min.js
PytorchZiranyuyanChuliFix1Fix1/js/reader.min.map
PytorchZiranyuyanChuliFix1Fix1/js/hooks/__init__.py
PytorchZiranyuyanChuliFix1Fix1/js/hooks/extensions/__init__.py
pytorch_ziranyuyan_chuli_fix1_fix1-2025.3.25.0.dist-info/METADATA
pytorch_ziranyuyan_chuli_fix1_fix1-2025.3.25.0.dist-info/WHEEL
pytorch_ziranyuyan_chuli_fix1_fix1-2025.3.25.0.dist-info/entry_points.txt
pytorch_ziranyuyan_chuli_fix1_fix1-2025.3.25.0.dist-info/top_level.txt
pytorch_ziranyuyan_chuli_fix1_fix1-2025.3.25.0.dist-info/RECORD
